Metadata-Version: 2.4
Name: llama-index-vector-stores-databricks
Version: 0.5.1
Summary: llama-index vector_stores databricks vector search integration
Author: Alberto Da Costa <alberto@bamelevate.com>, Nickhil Nabar <nickhil@bamelevate.com
License-Expression: MIT
License-File: LICENSE
Requires-Python: <4.0,>=3.9
Requires-Dist: databricks-vectorsearch<0.22,>=0.21
Requires-Dist: llama-index-core<0.15,>=0.13.0
